{"timeline":{"headline":"A day like today. <b>16-07<\/b>","type":"default","text":"See what happened a day like today with data from Wikipedia and DBpedia!","date":[{"startDate":"1890,07,16","dbpedia":"http:\/\/it.dbpedia.org\/resource\/Peter_Clemenza","headline":"Peter Clemenza (Birth)","text":"<p style='text-align: justify;'>Peter Clemenza è un personaggio di finzione del romanzo di Mario Puzo Il padrino. Nella saga cinematografica è interpretato dall'attore Richard Castellano e da Bruno Kirby. Nella versione classica italiana è doppiato da Mario Laurentino (da adulto) e da Vittorio Stagni (da giovane) mentre nella riedizione del primo film del 2008 è doppiato da Giorgio Lopez. <br><br><a href='http:\/\/it.wikipedia.org\/wiki\/Peter_Clemenza' target='_blank'>Read more...<\/a><br><a href='http:\/\/it.dbpedia.org\/resource\/Peter_Clemenza' target='_blank'>Take a look at DBpedia...<\/a><\/p>","asset":{"media":"img\/no_image_available.png","credit":"","caption":"Peter Clemenza","thumbnail":"http:\/\/upload.wikimedia.org\/wikipedia\/commons\/thumb\/2\/29\/Peter_Clemenza.png\/200px-Peter_Clemenza.png"}}]}}