{"timeline":{"headline":"A day like today. <b>19-07<\/b>","type":"default","text":"See what happened a day like today with data from Wikipedia and DBpedia!","date":[{"startDate":"1954,07,19","dbpedia":"http:\/\/it.dbpedia.org\/resource\/Il_Freddo","headline":"Il Freddo (Birth)","text":"<p style='text-align: justify;'>Il Freddo, vero nome Fabrizio Soleri, è un personaggio letterario, protagonista del libro di Giancarlo De Cataldo, Romanzo criminale, ispirato alla vera storia della banda della Magliana, che operò in Italia a Roma tra la fine degli anni settanta ed il 1990. Il personaggio del Freddo è ispirato a Maurizio Abbatino, uno dei capi storici, e, insieme a Marcello Colafigli e ad Antonio Mancini, ultimo rimasto in vita. <br><br><a href='http:\/\/it.wikipedia.org\/wiki\/Il_Freddo' target='_blank'>Read more...<\/a><br><a href='http:\/\/it.dbpedia.org\/resource\/Il_Freddo' target='_blank'>Take a look at DBpedia...<\/a><\/p>","asset":{"media":"img\/no_image_available.png","credit":"","caption":"Il Freddo","thumbnail":"http:\/\/upload.wikimedia.org\/wikipedia\/commons\/thumb\/c\/cb\/Ilfreddo.png\/200px-Ilfreddo.png"}},{"startDate":"1963,07,19","dbpedia":"http:\/\/it.dbpedia.org\/resource\/Mark_Greene","headline":"Mark Greene (Birth)","text":"<p style='text-align: justify;'>Mark Greene è un personaggio della serie televisiva E.R. - Medici in prima linea, interpretato da Anthony Edwards. È stato considerato protagonista per le prime otto stagioni. Mark, figlio unico, è cresciuto con sua madre Ruth e suo padre David, lei cattolica non praticante, lui ebreo agnostico. Il padre ha servito la marina americana, perciò la sua famiglia ha dovuto spostarsi spesso. <br><br><a href='http:\/\/it.wikipedia.org\/wiki\/Mark_Greene' target='_blank'>Read more...<\/a><br><a href='http:\/\/it.dbpedia.org\/resource\/Mark_Greene' target='_blank'>Take a look at DBpedia...<\/a><\/p>","asset":{"media":"img\/no_image_available.png","credit":"","caption":"Mark Greene","thumbnail":"http:\/\/upload.wikimedia.org\/wikipedia\/commons\/thumb\/6\/6a\/Mark_Greene.jpg\/200px-Mark_Greene.jpg"}}]}}